Pytonium/__init__.py
Pytonium/bin_linux.zip
Pytonium/bin_win.zip
Pytonium/pytonium.cp311-win_amd64.pyd
Pytonium/pytonium.pyi
Pytonium/bin_linux/chrome-sandbox
Pytonium/bin_linux/chrome_100_percent.pak
Pytonium/bin_linux/chrome_200_percent.pak
Pytonium/bin_linux/icudtl.dat
Pytonium/bin_linux/libEGL.so
Pytonium/bin_linux/libGLESv2.so
Pytonium/bin_linux/libcef.so
Pytonium/bin_linux/libvk_swiftshader.so
Pytonium/bin_linux/libvulkan.so.1
Pytonium/bin_linux/pytonium_subprocess
Pytonium/bin_linux/resources.pak
Pytonium/bin_linux/snapshot_blob.bin
Pytonium/bin_linux/v8_context_snapshot.bin
Pytonium/bin_linux/vk_swiftshader_icd.json
Pytonium/bin_linux/locales/af.pak
Pytonium/bin_linux/locales/am.pak
Pytonium/bin_linux/locales/ar.pak
Pytonium/bin_linux/locales/bg.pak
Pytonium/bin_linux/locales/bn.pak
Pytonium/bin_linux/locales/ca.pak
Pytonium/bin_linux/locales/cs.pak
Pytonium/bin_linux/locales/da.pak
Pytonium/bin_linux/locales/de.pak
Pytonium/bin_linux/locales/el.pak
Pytonium/bin_linux/locales/en-GB.pak
Pytonium/bin_linux/locales/en-US.pak
Pytonium/bin_linux/locales/es-419.pak
Pytonium/bin_linux/locales/es.pak
Pytonium/bin_linux/locales/et.pak
Pytonium/bin_linux/locales/fa.pak
Pytonium/bin_linux/locales/fi.pak
Pytonium/bin_linux/locales/fil.pak
Pytonium/bin_linux/locales/fr.pak
Pytonium/bin_linux/locales/gu.pak
Pytonium/bin_linux/locales/he.pak
Pytonium/bin_linux/locales/hi.pak
Pytonium/bin_linux/locales/hr.pak
Pytonium/bin_linux/locales/hu.pak
Pytonium/bin_linux/locales/id.pak
Pytonium/bin_linux/locales/it.pak
Pytonium/bin_linux/locales/ja.pak
Pytonium/bin_linux/locales/kn.pak
Pytonium/bin_linux/locales/ko.pak
Pytonium/bin_linux/locales/lt.pak
Pytonium/bin_linux/locales/lv.pak
Pytonium/bin_linux/locales/ml.pak
Pytonium/bin_linux/locales/mr.pak
Pytonium/bin_linux/locales/ms.pak
Pytonium/bin_linux/locales/nb.pak
Pytonium/bin_linux/locales/nl.pak
Pytonium/bin_linux/locales/pl.pak
Pytonium/bin_linux/locales/pt-BR.pak
Pytonium/bin_linux/locales/pt-PT.pak
Pytonium-0.0.13.dist-info/METADATA
Pytonium-0.0.13.dist-info/WHEEL
Pytonium-0.0.13.dist-info/top_level.txt
Pytonium-0.0.13.dist-info/RECORD
