Metadata-Version: 2.1
Name: Pytonium
Version: 0.0.13
Summary: A framework for building python apps, with a GUI based on the web-technologies HTML, CSS and Javascript.
Author-email: Maximilian Winter <maximilian.winter.91@gmail.com>
Project-URL: Homepage, https://github.com/Maximilian-Winter/pytonium
Project-URL: Bug Tracker, https://github.com/Maximilian-Winter/pytonium/issues
Classifier: Programming Language :: Python :: 3
Classifier: License :: OSI Approved :: BSD License
Classifier: Operating System :: Microsoft :: Windows
Classifier: Operating System :: POSIX :: Linux
Requires-Python: >=3.10
